src/__init__.py
src/main.py
src/assistants/__init__.py
src/assistants/openai_assistant.py
src/base/__init__.py
src/base/llm_base.py
src/utils/__init__.py
src/utils/config_loader.py
openai_wds_chat-0.1.0.dist-info/LICENSE
openai_wds_chat-0.1.0.dist-info/METADATA
openai_wds_chat-0.1.0.dist-info/WHEEL
openai_wds_chat-0.1.0.dist-info/entry_points.txt
openai_wds_chat-0.1.0.dist-info/top_level.txt
openai_wds_chat-0.1.0.dist-info/RECORD
