Metadata-Version: 2.1
Name: openai-wds-chat
Version: 0.1.0
Summary: A flexible OpenAI API wrapper with multi-role support and context management
Home-page: https://github.com/wds-dxh/openai-wds
Author: wds-Ubuntu22-cqu
Author-email: wdsnpshy@163.com
Classifier: Development Status :: 3 - Alpha
Classifier: Intended Audience :: Developers
Classifier: License :: OSI Approved :: MIT License
Classifier: Operating System :: OS Independent
Classifier: Programming Language :: Python :: 3
Classifier: Programming Language :: Python :: 3.8
Classifier: Programming Language :: Python :: 3.9
Classifier: Programming Language :: Python :: 3.10
Classifier: Topic :: Software Development :: Libraries :: Python Modules
Classifier: Topic :: Scientific/Engineering :: Artificial Intelligence
Requires-Python: >=3.8
License-File: LICENSE
Requires-Dist: openai>=1.0.0
Requires-Dist: pydantic>=2.0.0
Requires-Dist: python-dotenv>=0.19.0
Requires-Dist: tenacity>=8.0.0
